{
  "schema_version": "1.0.0",
  "exported_at": "2026-04-24T10:01:36Z",
  "index_freshness": "2026-04-24T10:00:01.580Z",
  "protocol_address": "r9XYDxJDbmmhSGNpUguVhea6xn3Tu2HbeF",
  "treasury_address": "rsS2Y6CK9dz9dVFjJvRyD2gBdoLPqjaXRZ",
  "protocol_fee_bps": 250,
  "protocol_fee_pct": "2.5%",
  "services": [
    {
      "service_id": "herald",
      "name": "The Hive Herald",
      "description": "Daily intelligence briefing delivered to your inbox and available at pft.permanentupperclass.com/herald/. Flow tracking, contributor movers, sybil watch, full-history deep cuts. The newspaper of the Post Fiat colony.",
      "url": "https://pft.permanentupperclass.com/herald/",
      "preview_image": "/herald/edition-preview.jpg",
      "provider": "Permanent Upper Class",
      "provider_address": "rsS2Y6CK9dz9dVFjJvRyD2gBdoLPqjaXRZ",
      "service_address": "r9XYDxJDbmmhSGNpUguVhea6xn3Tu2HbeF",
      "price_pft": 1000,
      "price_drops": 1000000000,
      "period_days": 30,
      "features": [
        "Daily intelligence briefing delivered on-chain",
        "Flow of Capital: reward tracking, top earners, distribution analysis",
        "Movers: rising contributors, new wallets, gone-quiet alerts",
        "Sybil Watch: bot detection, enforcement state, review queue",
        "Deep Cut: full-history archive exclusives only we can produce",
        "Historical archive access at /herald/{date}"
      ],
      "free_features": [
        "Pulse: network health, wallet count, memo velocity"
      ],
      "status": "active",
      "verified": true,
      "registered_at": "2026-04-14T00:00:00Z",
      "subscribers_active": 3,
      "subscribers_lifetime": 3,
      "revenue_30d_pft": 3000.0,
      "revenue_30d_protocol_fee_pft": 75.0
    }
  ],
  "bundles": [],
  "protocol": {
    "memo_type_subscribe": "subs.subscribe",
    "memo_type_register": "subs.register",
    "memo_type_forward": "subs.forward",
    "verification_method": "canonical_chain_query",
    "payment_semantics": "one_payment_one_period",
    "cancellation": "non_renewal",
    "rounding_policy": "floor",
    "spec_url": "https://github.com/P-U-C/pft-validator/blob/main/subs-protocol.md"
  },
  "stats": {
    "total_services": 1,
    "total_active_subscriptions": 3,
    "total_revenue_30d_pft": 3000.0,
    "total_protocol_revenue_30d_pft": 75.0
  }
}